tskit_arg_visualizer/__init__.py
tskit_arg_visualizer/visualizer.css
tskit_arg_visualizer/visualizer.js
tskit_arg_visualizer/alternative_plots/edge_spans.js
tskit_arg_visualizer/alternative_plots/genome_bar.js
tskit_arg_visualizer-0.1.2.dist-info/licenses/LICENSE
tskit_arg_visualizer-0.1.2.dist-info/METADATA
tskit_arg_visualizer-0.1.2.dist-info/WHEEL
tskit_arg_visualizer-0.1.2.dist-info/top_level.txt
tskit_arg_visualizer-0.1.2.dist-info/RECORD
