Metadata-Version: 2.4
Name: tskit_arg_visualizer
Version: 0.1.2
Summary: Interactive visualization method for ancestral recombination graphs
Author-email: James Kitchens <kitchensjn@gmail.com>
Project-URL: Homepage, https://github.com/kitchensjn/tskit_arg_visualizer
Project-URL: Changelog, https://github.com/kitchensjn/tskit_arg_visualizer/blob/main/CHANGELOG.rst
Project-URL: Bug Tracker, https://github.com/kitchensjn/tskit_arg_visualizer/issues
Keywords: population genetics,tree sequence,ancestral recombination graph,visualization,D3.js
Classifier: Programming Language :: Python
Classifier: Programming Language :: Python :: 3
Classifier: Programming Language :: Python :: 3.7
Classifier: Programming Language :: Python :: 3.8
Classifier: Programming Language :: Python :: 3.9
Classifier: Programming Language :: Python :: 3.10
Classifier: Programming Language :: Python :: 3 :: Only
Classifier: License :: OSI Approved :: MIT License
Classifier: Development Status :: 3 - Alpha
Classifier: Environment :: Other Environment
Classifier: Intended Audience :: Science/Research
Classifier: Operating System :: POSIX
Classifier: Operating System :: MacOS :: MacOS X
Classifier: Operating System :: Microsoft :: Windows
Classifier: Topic :: Scientific/Engineering
Classifier: Topic :: Scientific/Engineering :: Bio-Informatics
Requires-Python: >=3.7
License-File: LICENSE
Requires-Dist: pandas
Requires-Dist: msprime
Requires-Dist: IPython
Requires-Dist: tqdm
Dynamic: license-file
